LICENSE.txt
README.rst
setup.cfg
setup.py
M_LOOP.egg-info/PKG-INFO
M_LOOP.egg-info/SOURCES.txt
M_LOOP.egg-info/dependency_links.txt
M_LOOP.egg-info/entry_points.txt
M_LOOP.egg-info/requires.txt
M_LOOP.egg-info/top_level.txt
mloop/__init__.py
mloop/cmd.py
mloop/controllers.py
mloop/interfaces.py
mloop/launchers.py
mloop/learners.py
mloop/neuralnet.py
mloop/testing.py
mloop/utilities.py
mloop/visualizations.py
tests/test_examples.py
tests/test_units.py