Metadata-Version: 2.1
Name: M-LOOP
Version: 3.3.4
Summary: M-LOOP: Machine-learning online optimization package. A python package of automated optimization tools - enhanced with machine-learning - for quantum scientific experiments, computer controlled systems or other optimization tasks.
Home-page: https://github.com/michaelhush/M-LOOP/
Download-URL: https://github.com/michaelhush/M-LOOP/tarball/v3.3.4
Author: Michael R Hush
Author-email: MichaelRHush@gmail.com
License: MIT
Keywords: automated machine learning optimization optimisation science experiment quantum
Platform: UNKNOWN
Classifier: Development Status :: 2 - Pre-Alpha
Classifier: Intended Audience :: Science/Research
Classifier: Intended Audience :: Manufacturing
Classifier: License :: OSI Approved :: MIT License
Classifier: Natural Language :: English
Classifier: Operating System :: MacOS :: MacOS X
Classifier: Operating System :: POSIX :: Linux
Classifier: Operating System :: Microsoft :: Windows
Classifier: Programming Language :: Python :: 2.7
Classifier: Programming Language :: Python :: 3.4
Classifier: Programming Language :: Python :: 3.5
Classifier: Programming Language :: Python :: Implementation :: CPython
Classifier: Topic :: Scientific/Engineering
Classifier: Topic :: Scientific/Engineering :: Artificial Intelligence
Classifier: Topic :: Scientific/Engineering :: Physics
License-File: LICENSE.txt
